tumor_detection/__init__.py
tumor_detection/config.py
tumor_detection/cli/__init__.py
tumor_detection/cli/infer.py
tumor_detection/cli/train.py
tumor_detection/inference/__init__.py
tumor_detection/inference/api.py
tumor_detection/utils/__init__.py
tumor_detection/utils/device.py
tumor_detection_segmentation-2.0.0.dist-info/METADATA
tumor_detection_segmentation-2.0.0.dist-info/WHEEL
tumor_detection_segmentation-2.0.0.dist-info/entry_points.txt
tumor_detection_segmentation-2.0.0.dist-info/licenses/LICENSE
tumor_detection_segmentation-2.0.0.dist-info/RECORD
