Metadata-Version: 2.4
Name: tumor-detection-segmentation
Version: 2.0.0
Summary: Advanced Medical Imaging AI Platform for tumor detection and segmentation
Project-URL: Homepage, https://github.com/hkevin01/tumor-detection-segmentation
Project-URL: Documentation, https://github.com/hkevin01/tumor-detection-segmentation/docs
Project-URL: Repository, https://github.com/hkevin01/tumor-detection-segmentation.git
Project-URL: Issues, https://github.com/hkevin01/tumor-detection-segmentation/issues
Author-email: Medical Imaging AI Team <team@medical-ai.org>
Maintainer-email: Kevin <hkevin01@github.com>
License: MIT License
License-File: LICENSE
Keywords: ai,dicom,medical-imaging,monai,segmentation,tumor-detection
Classifier: Development Status :: 4 - Beta
Classifier: Intended Audience :: Healthcare Industry
Classifier: Intended Audience :: Science/Research
Classifier: License :: OSI Approved :: MIT License
Classifier: Operating System :: OS Independent
Classifier: Programming Language :: Python :: 3
Classifier: Programming Language :: Python :: 3.8
Classifier: Programming Language :: Python :: 3.9
Classifier: Programming Language :: Python :: 3.10
Classifier: Programming Language :: Python :: 3.11
Classifier: Programming Language :: Python :: 3.12
Classifier: Topic :: Scientific/Engineering :: Artificial Intelligence
Classifier: Topic :: Scientific/Engineering :: Medical Science Apps.
Requires-Python: >=3.8
Requires-Dist: matplotlib>=3.5.0
Requires-Dist: monai>=1.3.0
Requires-Dist: nibabel>=4.0.0
Requires-Dist: numpy>=1.21.0
Requires-Dist: pandas>=1.4.0
Requires-Dist: pathlib2>=2.3.0; python_version < '3.4'
Requires-Dist: pillow>=9.0.0
Requires-Dist: pyyaml>=6.0
Requires-Dist: scikit-image>=0.19.0
Requires-Dist: scipy>=1.8.0
Requires-Dist: seaborn>=0.11.0
Requires-Dist: simpleitk>=2.2.0
Requires-Dist: torch>=1.12.0
Requires-Dist: torchvision>=0.13.0
Requires-Dist: tqdm>=4.64.0
Requires-Dist: typing-extensions>=4.0.0
Provides-Extra: all
Requires-Dist: black>=23.7.0; extra == 'all'
Requires-Dist: cryptography>=41.0.4; extra == 'all'
Requires-Dist: dash>=2.14.0; extra == 'all'
Requires-Dist: fastapi>=0.103.0; extra == 'all'
Requires-Dist: fhir-resources>=7.0.2; extra == 'all'
Requires-Dist: jinja2>=3.1.2; extra == 'all'
Requires-Dist: mypy>=1.5.1; extra == 'all'
Requires-Dist: plotly>=5.15.0; extra == 'all'
Requires-Dist: pre-commit>=3.3.0; extra == 'all'
Requires-Dist: pydantic>=2.4.0; extra == 'all'
Requires-Dist: pydicom>=2.4.3; extra == 'all'
Requires-Dist: pyjwt>=2.8.0; extra == 'all'
Requires-Dist: pynetdicom>=2.0.2; extra == 'all'
Requires-Dist: pytest-cov>=4.1.0; extra == 'all'
Requires-Dist: pytest-mock>=3.11.1; extra == 'all'
Requires-Dist: pytest>=7.4.0; extra == 'all'
Requires-Dist: python-docx>=0.8.11; extra == 'all'
Requires-Dist: reportlab>=4.0.4; extra == 'all'
Requires-Dist: ruff>=0.0.287; extra == 'all'
Requires-Dist: sqlalchemy>=2.0.21; extra == 'all'
Requires-Dist: streamlit>=1.28.0; extra == 'all'
Requires-Dist: uvicorn>=0.23.0; extra == 'all'
Provides-Extra: api
Requires-Dist: fastapi>=0.103.0; extra == 'api'
Requires-Dist: pydantic>=2.4.0; extra == 'api'
Requires-Dist: uvicorn>=0.23.0; extra == 'api'
Provides-Extra: clinical
Requires-Dist: cryptography>=41.0.4; extra == 'clinical'
Requires-Dist: fhir-resources>=7.0.2; extra == 'clinical'
Requires-Dist: jinja2>=3.1.2; extra == 'clinical'
Requires-Dist: pydicom>=2.4.3; extra == 'clinical'
Requires-Dist: pyjwt>=2.8.0; extra == 'clinical'
Requires-Dist: pynetdicom>=2.0.2; extra == 'clinical'
Requires-Dist: python-docx>=0.8.11; extra == 'clinical'
Requires-Dist: reportlab>=4.0.4; extra == 'clinical'
Requires-Dist: sqlalchemy>=2.0.21; extra == 'clinical'
Provides-Extra: dev
Requires-Dist: black>=23.7.0; extra == 'dev'
Requires-Dist: mypy>=1.5.1; extra == 'dev'
Requires-Dist: pre-commit>=3.3.0; extra == 'dev'
Requires-Dist: pytest-cov>=4.1.0; extra == 'dev'
Requires-Dist: pytest-mock>=3.11.1; extra == 'dev'
Requires-Dist: pytest>=7.4.0; extra == 'dev'
Requires-Dist: ruff>=0.0.287; extra == 'dev'
Provides-Extra: gui
Requires-Dist: dash>=2.14.0; extra == 'gui'
Requires-Dist: plotly>=5.15.0; extra == 'gui'
Requires-Dist: streamlit>=1.28.0; extra == 'gui'
